[
    {
        "baseDate": "20241001",
        "macAddress": "9b854daab88e2de056b966b97c565806b183f4f2249365759833edf685f821ab",
        "apGroupName": "서귀포 치유의 숲",
        "installLocationDetail": "힐링센타 D동 2층 (삼나무체험실)",
        "category": "숲길",
        "categoryDetail": "숲길",
        "addressDong": "제주특별자치도 서귀포시 호근동",
        "addressDetail": "서귀포시 호근동 산 4(산록남로 2271)",
        "latitude": "33.300788",
        "longitude": "126.518843"
    },
    {
        "baseDate": "20241001",
        "macAddress": "46b3ed3c8f1e78f3233737d0ebc6519374b586cbecdb26920a929598ecb203f3",
        "apGroupName": "서귀포 치유의 숲",
        "installLocationDetail": "방문자센타 '차롱' 쉼터 내",
        "category": "숲길",
        "categoryDetail": "숲길",
        "addressDong": "제주특별자치도 서귀포시 호근동",
        "addressDetail": "서귀포시 호근동 산 4(산록남로 2271)",
        "latitude": "33.29196",
        "longitude": "126.527954"
    },
    {
        "baseDate": "20241001",
        "macAddress": "234e4eb4a1cae1314dbba456a401d1db688c4455947429689acb91aa531ba376",
        "apGroupName": "사려니숲길",
        "installLocationDetail": "교통단속CCTV 폴 - 동 건너편정류장 방향",
        "category": "숲길",
        "categoryDetail": "숲길",
        "addressDong": "제주특별자치도 서귀포시 표선면 가시리",
        "addressDetail": "서귀포시 표선면 가시리 산 158(남조로 붉은오름사려니숲길 입구)",
        "latitude": "33.395281",
        "longitude": "126.685351"
    },
    {
        "baseDate": "20241001",
        "macAddress": "5a3167aec5ae70b2ff51e4828d647455e760036bf60cdc94158dcfa9c1693606",
        "apGroupName": "사려니숲길",
        "installLocationDetail": "가로등",
        "category": "숲길",
        "categoryDetail": "숲길",
        "addressDong": "제주특별자치도 제주시 봉개동",
        "addressDetail": "제주시 봉개동 2750-2(사려니숲길 주차장)",
        "latitude": "33.433516",
        "longitude": "126.63786"
    },
    {
        "baseDate": "20241001",
        "macAddress": "43b0215e953e4534e777821a37a53830368b5e39af9655d84870e3604bf16dba",
        "apGroupName": "한라생태숲",
        "installLocationDetail": "관리시험연구동 지붕 북",
        "category": "숲길",
        "categoryDetail": "숲길",
        "addressDong": "제주특별자치도 제주시 용강동",
        "addressDetail": "제주시 516로 2596(용강동)",
        "latitude": "33.43109",
        "longitude": "126.596183"
    },
    {
        "baseDate": "20241001",
        "macAddress": "a1f3ac37419536c28485681fceddfc063af24863f1a6b146694da7331b1bace5",
        "apGroupName": "사려니숲길",
        "installLocationDetail": "가로등",
        "category": "숲길",
        "categoryDetail": "숲길",
        "addressDong": "제주특별자치도 제주시 봉개동",
        "addressDetail": "제주시 봉개동 2750-2(사려니숲길 주차장)",
        "latitude": "33.43411",
        "longitude": "126.637887"
    },
    {
        "baseDate": "20241001",
        "macAddress": "5a3167aec5ae70b2ff51e4828d647455e760036bf60cdc94158dcfa9c1693606",
        "apGroupName": "사려니숲길",
        "installLocationDetail": "가로등",
        "category": "숲길",
        "categoryDetail": "숲길",
        "addressDong": "제주특별자치도 제주시 봉개동",
        "addressDetail": "제주시 봉개동 2750-2(사려니숲길 주차장)",
        "latitude": "33.433516",
        "longitude": "126.63786"
    },
    {
        "baseDate": "20241001",
        "macAddress": "6a54e4b1467e00e6ab665787f53a1f39fa223ba86d17d3750a5c621da5b75f59",
        "apGroupName": "서귀포 치유의 숲",
        "installLocationDetail": "힐링하우스 5동",
        "category": "숲길",
        "categoryDetail": "숲길",
        "addressDong": "제주특별자치도 서귀포시 호근동",
        "addressDetail": "서귀포시 호근동 산 4(산록남로 2271)",
        "latitude": "33.291889",
        "longitude": "126.525733"
    },
    {
        "baseDate": "20241001",
        "macAddress": "a4813cb7e202fcd25d93470cdd79749d6aa7697c1c04749ec9fd0010e10cccae",
        "apGroupName": "서귀포 치유의 숲",
        "installLocationDetail": "방문자센타 옥상 - 남서",
        "category": "숲길",
        "categoryDetail": "숲길",
        "addressDong": "제주특별자치도 서귀포시 호근동",
        "addressDetail": "서귀포시 산록남로 2271",
        "latitude": "33.291695",
        "longitude": "126.527521"
    },
    {
        "baseDate": "20241001",
        "macAddress": "67375431fa004ae6b2f1a1653ec6bdbb8bcd74d7bef4f50b5577c8dcc273f75c",
        "apGroupName": "사려니숲길",
        "installLocationDetail": "ip주 숲길 입구방향",
        "category": "숲길",
        "categoryDetail": "숲길",
        "addressDong": "제주특별자치도 서귀포시 표선면 가시리",
        "addressDetail": "서귀포시 표선면 가시리 산 158",
        "latitude": "33.394944",
        "longitude": "126.683846"
    },
    {
        "baseDate": "20241001",
        "macAddress": "9b854daab88e2de056b966b97c565806b183f4f2249365759833edf685f821ab",
        "apGroupName": "서귀포 치유의 숲",
        "installLocationDetail": "힐링센타 D동 2층 (삼나무체험실)",
        "category": "숲길",
        "categoryDetail": "숲길",
        "addressDong": "제주특별자치도 서귀포시 호근동",
        "addressDetail": "서귀포시 호근동 산 4(산록남로 2271)",
        "latitude": "33.300788",
        "longitude": "126.518843"
    },
    {
        "baseDate": "20241001",
        "macAddress": "234e4eb4a1cae1314dbba456a401d1db688c4455947429689acb91aa531ba376",
        "apGroupName": "사려니숲길",
        "installLocationDetail": "교통단속CCTV 폴 - 동 건너편정류장 방향",
        "category": "숲길",
        "categoryDetail": "숲길",
        "addressDong": "제주특별자치도 서귀포시 표선면 가시리",
        "addressDetail": "서귀포시 표선면 가시리 산 158(남조로 붉은오름사려니숲길 입구)",
        "latitude": "33.395281",
        "longitude": "126.685351"
    },
    {
        "baseDate": "20241001",
        "macAddress": "5a3167aec5ae70b2ff51e4828d647455e760036bf60cdc94158dcfa9c1693606",
        "apGroupName": "사려니숲길",
        "installLocationDetail": "가로등",
        "category": "숲길",
        "categoryDetail": "숲길",
        "addressDong": "제주특별자치도 제주시 봉개동",
        "addressDetail": "제주시 봉개동 2750-2(사려니숲길 주차장)",
        "latitude": "33.433516",
        "longitude": "126.63786"
    },
    {
        "baseDate": "20241001",
        "macAddress": "c4fbd7a486ccbfbb0eabac428470eb2f3706bc42e5c50ed11fb7f1553ce39172",
        "apGroupName": "서귀포 치유의 숲",
        "installLocationDetail": "힐링하우스 7동",
        "category": "숲길",
        "categoryDetail": "숲길",
        "addressDong": "제주특별자치도 서귀포시 호근동",
        "addressDetail": "서귀포시 호근동 산 4(산록남로 2271)",
        "latitude": "33.291528",
        "longitude": "126.526753"
    },
    {
        "baseDate": "20241001",
        "macAddress": "fb044ad4f2e8aaada4621250a32cd3e22327d0c01d1cf20c5f1188847a917efa",
        "apGroupName": "서귀포 치유의 숲",
        "installLocationDetail": "힐링하우스 1동",
        "category": "숲길",
        "categoryDetail": "숲길",
        "addressDong": "제주특별자치도 서귀포시 호근동",
        "addressDetail": "서귀포시 호근동 산 4(산록남로 2271)",
        "latitude": "33.292473",
        "longitude": "126.527393"
    },
    {
        "baseDate": "20241001",
        "macAddress": "a97f368314b381a51c4e4eebabcb40dddc0a2b79fffd8769bd010929ab0daadb",
        "apGroupName": "사려니숲길",
        "installLocationDetail": "교통단속CCTV 폴 - 남 주차장방향",
        "category": "숲길",
        "categoryDetail": "숲길",
        "addressDong": "제주특별자치도 서귀포시 표선면 가시리",
        "addressDetail": "서귀포시 표선면 가시리 산 158(남조로 붉은오름사려니숲길 입구)",
        "latitude": "33.394782",
        "longitude": "126.685288"
    },
    {
        "baseDate": "20241001",
        "macAddress": "c220928019943b141549c40dd7ee5c8c18a975b33dc25519b9e1eee8f682fcde",
        "apGroupName": "한라생태숲",
        "installLocationDetail": "안내소 벽면 북",
        "category": "숲길",
        "categoryDetail": "숲길",
        "addressDong": "제주특별자치도 제주시 용강동",
        "addressDetail": "제주시 516로 2596(용강동)",
        "latitude": "33.430931",
        "longitude": "126.596935"
    },
    {
        "baseDate": "20241001",
        "macAddress": "e35ff08663acba7167b3e7e4eeb914a31923db9827ee59bf2f4119866f77ae33",
        "apGroupName": "선흘곶자왈 생태숲",
        "installLocationDetail": "동백동산습지센터 주차장 방향",
        "category": "숲길",
        "categoryDetail": "숲길",
        "addressDong": "제주특별자치도 제주시 조천읍 선흘리",
        "addressDetail": "제주시 조천읍 선흘리 924",
        "latitude": "33.509554",
        "longitude": "126.715273"
    },
    {
        "baseDate": "20241001",
        "macAddress": "7323c804b2c006691991c701797444eede95ba40e099f0d862759a4d8772a33d",
        "apGroupName": "서귀포 치유의 숲",
        "installLocationDetail": "방문자센타 옥상 - 남",
        "category": "숲길",
        "categoryDetail": "숲길",
        "addressDong": "제주특별자치도 서귀포시 호근동",
        "addressDetail": "서귀포시 산록남로 2271",
        "latitude": "33.291518",
        "longitude": "126.528191"
    },
    {
        "baseDate": "20241001",
        "macAddress": "c418be7281bc0baadd476c1f6812172a97fe871caec74616e4bd286c0a26fcb8",
        "apGroupName": "화순 곶자왈 생태탐방숲길",
        "installLocationDetail": "화장실 외벽",
        "category": "숲길",
        "categoryDetail": "숲길",
        "addressDong": "제주특별자치도 서귀포시 안덕면 화순리",
        "addressDetail": "서귀포시 안덕면 화순리 2045",
        "latitude": "33.264317",
        "longitude": "126.331227"
    },
    {
        "baseDate": "20241001",
        "macAddress": "3216304cca619fb9c24524a98696ee8c591c9e9d0701b2de0639b176de58b2c2",
        "apGroupName": "한라생태숲 #2-3",
        "installLocationDetail": "관리시험연구동 지붕 남서(남쪽 버스주차장 방향)",
        "category": "숲길",
        "categoryDetail": "숲길",
        "addressDong": "제주특별자치도 제주시 용강동",
        "addressDetail": "제주시 516로 2596(용강동)",
        "latitude": "33.430627",
        "longitude": "126.597004"
    },
    {
        "baseDate": "20241001",
        "macAddress": "46356c4137c205bdb7d5e4172932ff52aec5b91f59ba27655c0e4a68932eea86",
        "apGroupName": "서귀포 치유의 숲",
        "installLocationDetail": "방문자센타 옥상 - 북",
        "category": "숲길",
        "categoryDetail": "숲길",
        "addressDong": "제주특별자치도 서귀포시 호근동",
        "addressDetail": "서귀포시 산록남로 2271",
        "latitude": "33.292145",
        "longitude": "126.528169"
    },
    {
        "baseDate": "20241001",
        "macAddress": "0003fd3a38fcd45328cdbf8fcb6dfb3ed7493de26ef37a8a136a503730861027",
        "apGroupName": "서귀포 치유의 숲",
        "installLocationDetail": "화장실 옥상 - 북서",
        "category": "숲길",
        "categoryDetail": "숲길",
        "addressDong": "제주특별자치도 서귀포시 호근동",
        "addressDetail": "서귀포시 산록남로 2271",
        "latitude": "33.300594",
        "longitude": "126.520791"
    },
    {
        "baseDate": "20241001",
        "macAddress": "12eb671fb2d3250d5e9db5c24f59971b6bc61d7070b8ca8acc5af69d9d1eb130",
        "apGroupName": "서귀포 치유의 숲",
        "installLocationDetail": "힐링센타 D동 2층 (시청각실)",
        "category": "숲길",
        "categoryDetail": "숲길",
        "addressDong": "제주특별자치도 서귀포시 호근동",
        "addressDetail": "서귀포시 호근동 산 4(산록남로 2271)",
        "latitude": "33.300788",
        "longitude": "126.518843"
    },
    {
        "baseDate": "20241001",
        "macAddress": "11d08c3854eb28941b92793323d4fb05b5bf0c79b20f04d2e7fff54ce51a43e7",
        "apGroupName": "화순 곶자왈 생태탐방숲길",
        "installLocationDetail": "IP 주",
        "category": "숲길",
        "categoryDetail": "숲길",
        "addressDong": "제주특별자치도 서귀포시 안덕면 화순리",
        "addressDetail": "서귀포시 안덕면 화순리 2045",
        "latitude": "33.263553",
        "longitude": "126.332131"
    },
    {
        "baseDate": "20241001",
        "macAddress": "343c733f93d339787bb3657fff93abd0fd86358fd2ccd1b3b47f2fbaa08f0025",
        "apGroupName": "서귀포 치유의 숲",
        "installLocationDetail": "화장실 옥상 - 동",
        "category": "숲길",
        "categoryDetail": "숲길",
        "addressDong": "제주특별자치도 서귀포시 호근동",
        "addressDetail": "서귀포시 산록남로 2271",
        "latitude": "33.300562",
        "longitude": "126.521762"
    },
    {
        "baseDate": "20241001",
        "macAddress": "e54eadce5b9aebb5b56b44caee16d7a2168afaa85294ce6d764fc88295170610",
        "apGroupName": "사려니숲길",
        "installLocationDetail": "KT 전주 -숲속 방향",
        "category": "숲길",
        "categoryDetail": "숲길",
        "addressDong": "제주특별자치도 서귀포시 표선면 가시리",
        "addressDetail": "서귀포시 표선면 가시리 산 158(남조로 붉은오름사려니숲길 입구)",
        "latitude": "33.395375",
        "longitude": "126.684469"
    },
    {
        "baseDate": "20241001",
        "macAddress": "c74f3439cc7932faa5153657f26c1357cacbe5171803333c7a6d3ee7aa3622b8",
        "apGroupName": "사려니숲길",
        "installLocationDetail": "외벽",
        "category": "숲길",
        "categoryDetail": "숲길",
        "addressDong": "제주특별자치도 제주시 봉개동",
        "addressDetail": "제주시 봉개동 2750-2(사려니숲길 주차장)",
        "latitude": "33.43467",
        "longitude": "126.637335"
    },
    {
        "baseDate": "20241001",
        "macAddress": "36f3e8c8801566cc3ab617666a44801f68eaaa5acc21e65a2620590b824dc0cd",
        "apGroupName": "서귀포 치유의 숲",
        "installLocationDetail": "힐링하우스 2동",
        "category": "숲길",
        "categoryDetail": "숲길",
        "addressDong": "제주특별자치도 서귀포시 호근동",
        "addressDetail": "서귀포시 호근동 산 4(산록남로 2271)",
        "latitude": "33.292443",
        "longitude": "126.526885"
    },
    {
        "baseDate": "20241001",
        "macAddress": "2d3088bc827c6ae62869a326a8acd7d1184579ae91529a10c3c0f2ebaa0052b6",
        "apGroupName": "사려니숲길",
        "installLocationDetail": "ip주 숲길방향",
        "category": "숲길",
        "categoryDetail": "숲길",
        "addressDong": "제주특별자치도 서귀포시 표선면 가시리",
        "addressDetail": "서귀포시 표선면 가시리 산 158",
        "latitude": "33.395146",
        "longitude": "126.682747"
    },
    {
        "baseDate": "20241001",
        "macAddress": "224acfc57faad6f2222e219eadfa48ff47f6e4acb4c56028cafc35183332212b",
        "apGroupName": "서귀포 치유의 숲",
        "installLocationDetail": "힐링센타 D동 1층 (건강측정실)",
        "category": "숲길",
        "categoryDetail": "숲길",
        "addressDong": "제주특별자치도 서귀포시 호근동",
        "addressDetail": "서귀포시 호근동 산 4(산록남로 2271)",
        "latitude": "33.300788",
        "longitude": "126.518843"
    },
    {
        "baseDate": "20241001",
        "macAddress": "f8ae0a71696793aa5e468b4d2f951fa027f4cafe40e97f71586fe74eaaf8b5ef",
        "apGroupName": "서귀포 치유의 숲",
        "installLocationDetail": "힐링하우스 3동",
        "category": "숲길",
        "categoryDetail": "숲길",
        "addressDong": "제주특별자치도 서귀포시 호근동",
        "addressDetail": "서귀포시 호근동 산 4(산록남로 2271)",
        "latitude": "33.292349",
        "longitude": "126.52637"
    },
    {
        "baseDate": "20241001",
        "macAddress": "d3b663e2a4362f0d89ca03cace4b1856a7311140272ae735c6d38dbe5e3596df",
        "apGroupName": "사려니숲길",
        "installLocationDetail": "교통단속CCTV 폴 - 북 주차장방향",
        "category": "숲길",
        "categoryDetail": "숲길",
        "addressDong": "제주특별자치도 서귀포시 표선면 가시리",
        "addressDetail": "서귀포시 표선면 가시리 산 158(남조로 붉은오름사려니숲길 입구)",
        "latitude": "33.395679",
        "longitude": "126.68492"
    },
    {
        "baseDate": "20241001",
        "macAddress": "92bcd79f789ea48eba513bdad592a345d87a1979d5ffaedb08bc9292f3fa7b5d",
        "apGroupName": "선흘곶자왈 생태숲",
        "installLocationDetail": "동백동산습지센터 내부",
        "category": "숲길",
        "categoryDetail": "숲길",
        "addressDong": "제주특별자치도 제주시 조천읍 선흘리",
        "addressDetail": "제주시 조천읍 선흘리 924",
        "latitude": "33.509606",
        "longitude": "126.715608"
    },
    {
        "baseDate": "20241001",
        "macAddress": "cc9aca0dfe0881e2547f27e078e447c71a345a6818c73b0edd167c4592fc5488",
        "apGroupName": "한라생태숲",
        "installLocationDetail": "관리시험연구동 지붕 남",
        "category": "숲길",
        "categoryDetail": "숲길",
        "addressDong": "제주특별자치도 제주시 용강동",
        "addressDetail": "제주시 516로 2596(용강동)",
        "latitude": "33.430412",
        "longitude": "126.596768"
    },
    {
        "baseDate": "20241001",
        "macAddress": "a76b8e6adcd48f502359875e049b81e3a56e53419955bfce74bdbca1d7c74907",
        "apGroupName": "한라생태숲",
        "installLocationDetail": "관리시험연구동 지붕 서",
        "category": "숲길",
        "categoryDetail": "숲길",
        "addressDong": "제주특별자치도 제주시 용강동",
        "addressDetail": "제주시 516로 2596(용강동)",
        "latitude": "33.430362",
        "longitude": "126.595728"
    },
    {
        "baseDate": "20241001",
        "macAddress": "3a3f92860632ff21795d5abfeb1f777c0b53057b46711c83cce6d414810ba432",
        "apGroupName": "한라생태숲",
        "installLocationDetail": "관리시험연구동 내부",
        "category": "숲길",
        "categoryDetail": "숲길",
        "addressDong": "제주특별자치도 제주시 용강동",
        "addressDetail": "제주시 516로 2596(용강동)",
        "latitude": "33.430803",
        "longitude": "126.596469"
    },
    {
        "baseDate": "20241001",
        "macAddress": "05f623a82fa67e4b846b0bd4c0503f5caae6166a5a4074629df39be845174135",
        "apGroupName": "석굴암(천왕사 숲길)",
        "installLocationDetail": "충혼묘지 주차장 중계기 폴대 동(주차장 숲길 진입로)",
        "category": "숲길",
        "categoryDetail": "숲길",
        "addressDong": "제주특별자치도 제주시 노형동",
        "addressDetail": "제주시 노형동 산 21",
        "latitude": "33.410989",
        "longitude": "126.494005"
    },
    {
        "baseDate": "20241001",
        "macAddress": "ffd8e6745aa3157fb971fdf3d13c4205bee4aa0f5a877e86d45ef89afb5414d2",
        "apGroupName": "사려니숲길",
        "installLocationDetail": "ip주 공연장 방향",
        "category": "숲길",
        "categoryDetail": "숲길",
        "addressDong": "제주특별자치도 서귀포시 표선면 가시리",
        "addressDetail": "서귀포시 표선면 가시리 산 158",
        "latitude": "33.394355",
        "longitude": "126.683478"
    },
    {
        "baseDate": "20241001",
        "macAddress": "cb4785452f74e3e90e9b2d10bc4a40e38277e264112e66a4b32e3dd372260bd5",
        "apGroupName": "서귀포 치유의 숲",
        "installLocationDetail": "힐링센타 D동 2층 (프로그램운영실)",
        "category": "숲길",
        "categoryDetail": "숲길",
        "addressDong": "제주특별자치도 서귀포시 호근동",
        "addressDetail": "서귀포시 호근동 산 4(산록남로 2271)",
        "latitude": "33.300788",
        "longitude": "126.518843"
    },
    {
        "baseDate": "20241001",
        "macAddress": "26b650f03b2671d61a2b21c3c94ac7a8d59537abc4b66a770658e93e1f0bf8e9",
        "apGroupName": "서귀포 치유의 숲",
        "installLocationDetail": "힐링하우스 6동",
        "category": "숲길",
        "categoryDetail": "숲길",
        "addressDong": "제주특별자치도 서귀포시 호근동",
        "addressDetail": "서귀포시 호근동 산 4(산록남로 2271)",
        "latitude": "33.291572",
        "longitude": "126.52638"
    },
    {
        "baseDate": "20241001",
        "macAddress": "c4393e33ce6a08ffeb5e12d994c9603bcbbb4be508cf2400e0037beb21e28cff",
        "apGroupName": "석굴암(천왕사 숲길)",
        "installLocationDetail": "충혼묘지 주차장 중계기 폴대 북(주차장 숲길 진입로)",
        "category": "숲길",
        "categoryDetail": "숲길",
        "addressDong": "제주특별자치도 제주시 노형동",
        "addressDetail": "제주시 노형동 산 20",
        "latitude": "33.410989",
        "longitude": "126.494005"
    },
    {
        "baseDate": "20241001",
        "macAddress": "ddffa806cd3dcf7873355fbe952d79122f3622f3975c508c2e472c5abc705200",
        "apGroupName": "서귀포 치유의 숲",
        "installLocationDetail": "힐링센타 E동 (실내치유실:다담실)",
        "category": "숲길",
        "categoryDetail": "숲길",
        "addressDong": "제주특별자치도 서귀포시 호근동",
        "addressDetail": "서귀포시 호근동 산 4(산록남로 2271)",
        "latitude": "33.300576",
        "longitude": "126.518603"
    }
]